toothfairy_cli/README.md
toothfairy_cli/__init__.py
toothfairy_cli/api.py
toothfairy_cli/cli.py
toothfairy_cli/config.py
toothfairy_cli-1.3.0.dist-info/METADATA
toothfairy_cli-1.3.0.dist-info/WHEEL
toothfairy_cli-1.3.0.dist-info/entry_points.txt
toothfairy_cli-1.3.0.dist-info/top_level.txt
toothfairy_cli-1.3.0.dist-info/RECORD
