Metadata-Version: 2.4
Name: toothfairy-cli
Version: 1.3.0
Summary: Command-line interface for ToothFairyAI API
Author-email: ToothFairyAI <support@toothfairyai.com>
License: MIT
Project-URL: Homepage, https://gitea.toothfairyai.com/ToothFairyAI/tooth-fairy-website/toothfairy-cli
Project-URL: Repository, https://gitea.toothfairyai.com/ToothFairyAI/tooth-fairy-website/toothfairy-cli
Project-URL: Documentation, https://gitea.toothfairyai.com/ToothFairyAI/tooth-fairy-website/toothfairy-cli#readme
Project-URL: Issues, https://gitea.toothfairyai.com/ToothFairyAI/tooth-fairy-website/toothfairy-cli/issues
Project-URL: Releases, https://gitea.toothfairyai.com/ToothFairyAI/tooth-fairy-website/toothfairy-cli/releases
Keywords: toothfairy,ai,cli,api,chatbot,agent
Classifier: Development Status :: 4 - Beta
Classifier: Intended Audience :: Developers
Classifier: License :: OSI Approved :: MIT License
Classifier: Operating System :: OS Independent
Classifier: Programming Language :: Python :: 3
Classifier: Programming Language :: Python :: 3.7
Classifier: Programming Language :: Python :: 3.8
Classifier: Programming Language :: Python :: 3.9
Classifier: Programming Language :: Python :: 3.10
Classifier: Programming Language :: Python :: 3.11
Classifier: Topic :: Software Development :: Libraries :: Python Modules
Classifier: Topic :: Internet :: WWW/HTTP :: Dynamic Content
Classifier: Topic :: Communications :: Chat
Requires-Python: >=3.7
Requires-Dist: requests>=2.25.0
Requires-Dist: click>=8.0.0
Requires-Dist: python-dotenv>=0.19.0
Requires-Dist: rich>=12.0.0
Requires-Dist: pyyaml>=6.0
Requires-Dist: httpx>=0.24.0
Requires-Dist: httpx-sse>=0.3.0
Provides-Extra: dev
Requires-Dist: pytest>=7.0.0; extra == "dev"
Requires-Dist: pytest-cov>=4.0.0; extra == "dev"
Requires-Dist: black>=22.0.0; extra == "dev"
Requires-Dist: flake8>=5.0.0; extra == "dev"
Requires-Dist: isort>=5.10.0; extra == "dev"
Requires-Dist: build>=0.8.0; extra == "dev"
Requires-Dist: twine>=4.0.0; extra == "dev"
Requires-Dist: bump2version>=1.0.0; extra == "dev"
